mockplatform/__init__.py
mockplatform/app.py
mockplatform/resources/__init__.py
mockplatform/resources/homepage.py
mockplatform/resources/files/homepage.html
mockplatform-0.2.0.dist-info/LICENSE.md
mockplatform-0.2.0.dist-info/METADATA
mockplatform-0.2.0.dist-info/WHEEL
mockplatform-0.2.0.dist-info/entry_points.txt
mockplatform-0.2.0.dist-info/top_level.txt
mockplatform-0.2.0.dist-info/RECORD
